iregexp/__init__.py
iregexp/checker.py
iregexp-0.6.1.dist-info/LICENSE
iregexp-0.6.1.dist-info/METADATA
iregexp-0.6.1.dist-info/WHEEL
iregexp-0.6.1.dist-info/top_level.txt
iregexp-0.6.1.dist-info/RECORD
